virtual_fabric/__init__.py
virtual_fabric/virtual_fabric_core.py
virtual_fabric-0.1.0.dist-info/LICENSE
virtual_fabric-0.1.0.dist-info/METADATA
virtual_fabric-0.1.0.dist-info/WHEEL
virtual_fabric-0.1.0.dist-info/top_level.txt
virtual_fabric-0.1.0.dist-info/RECORD
