Metadata-Version: 2.1
Name: virtual-fabric
Version: 0.1.0
Summary: High level library used for smooth orchestration of virtual machines using fabric
Home-page: https://github.com/DovaX/virtual_fabric
Author: DovaX
Author-email: dovax.ai@gmail.com
Classifier: Programming Language :: Python :: 3
Classifier: License :: OSI Approved :: MIT License
Classifier: Operating System :: OS Independent
Requires-Python: >=3.6
License-File: LICENSE
Requires-Dist: fabric
